almasim/__init__.py
almasim/__version__.py
almasim/_run.py
almasim/_run.pyi
almasim/alma.py
almasim/alma.pyi
almasim/antenna_config/.DS_Store
almasim/antenna_config/antenna_coordinates.csv
almasim/antenna_config/cycle10/alma.cycle10.0.1.cfg
almasim/antenna_config/cycle10/alma.cycle10.0.2.cfg
almasim/antenna_config/cycle10/alma.cycle10.0.3.cfg
almasim/antenna_config/cycle10/alma.cycle10.0.4.cfg
almasim/antenna_config/cycle10/alma.cycle10.0.5.cfg
almasim/antenna_config/cycle10/alma.cycle10.0.6.cfg
almasim/antenna_config/cycle10/alma.cycle10.0.7.cfg
almasim/antenna_config/cycle10/alma.cycle10.0.8.cfg
almasim/antenna_config/cycle3/alma.cycle3.0.1.cfg
almasim/antenna_config/cycle3/alma.cycle3.0.2.cfg
almasim/antenna_config/cycle3/alma.cycle3.0.3.cfg
almasim/antenna_config/cycle3/alma.cycle3.0.4.cfg
almasim/antenna_config/cycle3/alma.cycle3.0.5.cfg
almasim/antenna_config/cycle3/alma.cycle3.0.6.cfg
almasim/antenna_config/cycle3/alma.cycle3.0.7.cfg
almasim/antenna_config/cycle3/alma.cycle3.0.8.cfg
almasim/antenna_config/cycle4/alma.cycle4.0.1.cfg
almasim/antenna_config/cycle4/alma.cycle4.0.2.cfg
almasim/antenna_config/cycle4/alma.cycle4.0.3.cfg
almasim/antenna_config/cycle4/alma.cycle4.0.4.cfg
almasim/antenna_config/cycle4/alma.cycle4.0.5.cfg
almasim/antenna_config/cycle4/alma.cycle4.0.6.cfg
almasim/antenna_config/cycle4/alma.cycle4.0.7.cfg
almasim/antenna_config/cycle4/alma.cycle4.0.8.cfg
almasim/antenna_config/cycle4/alma.cycle4.0.9.cfg
almasim/antenna_config/cycle5/alma.cycle5.0.1.cfg
almasim/antenna_config/cycle5/alma.cycle5.0.10.cfg
almasim/antenna_config/cycle5/alma.cycle5.0.2.cfg
almasim/antenna_config/cycle5/alma.cycle5.0.3.cfg
almasim/antenna_config/cycle5/alma.cycle5.0.4.cfg
almasim/antenna_config/cycle5/alma.cycle5.0.5.cfg
almasim/antenna_config/cycle5/alma.cycle5.0.6.cfg
almasim/antenna_config/cycle5/alma.cycle5.0.7.cfg
almasim/antenna_config/cycle5/alma.cycle5.0.8.cfg
almasim/antenna_config/cycle5/alma.cycle5.0.9.cfg
almasim-2.1.9.dist-info/LICENSE.md
almasim-2.1.9.dist-info/METADATA
almasim-2.1.9.dist-info/WHEEL
almasim-2.1.9.dist-info/RECORD
