Metadata-Version: 2.1
Name: almasim
Version: 2.1.9
Summary: An ALMA Simulation package for a more civilized era.
Home-page: https://github.com/MicheleDelliVeneri/ALMASim
Author: Michele Delli Veneri
Author-email: micheledelliveneri@gmail.com
Requires-Python: >=3.12.4
Classifier: Programming Language :: Python :: 3
Requires-Dist: Hdecompose
Requires-Dist: astromartini
Requires-Dist: astropy
Requires-Dist: dask
Requires-Dist: dask-expr
Requires-Dist: dask-jobqueue
Requires-Dist: distributed
Requires-Dist: h5py
Requires-Dist: kaggle
Requires-Dist: matplotlib
Requires-Dist: multiprocess
Requires-Dist: nifty8
Requires-Dist: numpy
Requires-Dist: pandas
Requires-Dist: paramiko
Requires-Dist: pyqt6
Requires-Dist: pysftp
Requires-Dist: pyvo
Requires-Dist: scipy
Requires-Dist: seaborn
Requires-Dist: setuptools
Requires-Dist: tenacity
Requires-Dist: tqdm
Project-URL: Documentation, https://almasim.readthedocs.io/en/latest
Project-URL: Repository, https://github.com/MicheleDelliVeneri/ALMASim
